setup.py
Flask_AppUtils.egg-info/PKG-INFO
Flask_AppUtils.egg-info/SOURCES.txt
Flask_AppUtils.egg-info/dependency_links.txt
Flask_AppUtils.egg-info/pbr.json
Flask_AppUtils.egg-info/requires.txt
Flask_AppUtils.egg-info/top_level.txt
Flask_AppUtils.egg-info/zip-safe
flask_apputils/__init__.py
flask_apputils/decorators.py
flask_apputils/helpers.py
flask_apputils/middlewares.py
flask_apputils/mimes.py
flask_apputils/routing.py
flask_apputils/validators.py