Metadata-Version: 1.1
Name: Flask-AppUtils
Version: 1.2.0
Summary: A collection of useful patterns and helpers for Flask applications
Home-page: http://github.com/kofrasa/flask-apputils
Author: Francis Asante
Author-email: kofrasa@gmail.com
License: BSD
Platform: any
Classifier: Development Status :: 4 - Beta
Classifier: Environment :: Web Environment
Classifier: Intended Audience :: Developers
Classifier: License :: OSI Approved :: BSD License
Classifier: Operating System :: OS Independent
Classifier: Programming Language :: Python
Classifier: Topic :: Internet :: WWW/HTTP :: Dynamic Content
Classifier: Topic :: Software Development :: Libraries :: Python Modules
